securitykey.py
securitykey-0.3.4.dist-info/METADATA
securitykey-0.3.4.dist-info/WHEEL
securitykey-0.3.4.dist-info/top_level.txt
securitykey-0.3.4.dist-info/RECORD
