Metadata-Version: 2.4
Name: securitykey
Version: 0.3.4
Summary: A Python module to generate and verify security keys for unique identification
Author: JTCoder8290
Author-email: jacktay.yujie@gmail.com
Classifier: Programming Language :: Python :: 3
Classifier: Operating System :: OS Independent
Requires-Python: >=3.6
Dynamic: author
Dynamic: author-email
Dynamic: classifier
Dynamic: description
Dynamic: description-content-type
Dynamic: requires-python
Dynamic: summary
